schoolyourself/__init__.py
schoolyourself/schoolyourself.py
schoolyourself/schoolyourself_lesson.py
schoolyourself/schoolyourself_review.py
schoolyourself/schoolyourself_review_test.py
schoolyourself/public/review_icon.png
schoolyourself/public/sylib.css
schoolyourself/public/sylib.js
schoolyourself/static/css/student_view.css
schoolyourself/static/js/lesson_student_view.js
schoolyourself/static/js/review_student_view.js
schoolyourself/static/js/studio_view.js
schoolyourself/templates/lesson_student_view.html
schoolyourself/templates/review_student_view.html
schoolyourself/templates/studio_view.html
schoolyourself_xblock-0.3.1.dist-info/AUTHORS
schoolyourself_xblock-0.3.1.dist-info/LICENSE
schoolyourself_xblock-0.3.1.dist-info/METADATA
schoolyourself_xblock-0.3.1.dist-info/WHEEL
schoolyourself_xblock-0.3.1.dist-info/entry_points.txt
schoolyourself_xblock-0.3.1.dist-info/top_level.txt
schoolyourself_xblock-0.3.1.dist-info/RECORD
