Metadata-Version: 2.1
Name: schoolyourself-xblock
Version: 0.3.1
Summary: School Yourself lesson player
License-File: LICENSE
License-File: AUTHORS
Requires-Dist: Mako
Requires-Dist: XBlock
Requires-Dist: xblock-utils
